lite_youtube_embed/__init__.py
lite_youtube_embed/embed.py
wagtail_lite_youtube_embed-0.3.0.dist-info/licenses/LICENSE
wagtail_lite_youtube_embed-0.3.0.dist-info/WHEEL
wagtail_lite_youtube_embed-0.3.0.dist-info/METADATA
wagtail_lite_youtube_embed-0.3.0.dist-info/RECORD
